keyboxchecker/__init__.py
keyboxchecker/__main__.py
keyboxchecker/aosp_ec.pem
keyboxchecker/aosp_rsa.pem
keyboxchecker/google.pem
keyboxchecker/knox.pem
keyboxchecker-1.3.1.dist-info/LICENSE
keyboxchecker-1.3.1.dist-info/METADATA
keyboxchecker-1.3.1.dist-info/WHEEL
keyboxchecker-1.3.1.dist-info/entry_points.txt
keyboxchecker-1.3.1.dist-info/RECORD
