Metadata-Version: 2.3
Name: keyboxchecker
Version: 1.3.1
Summary: 
Author: Li Hua
Author-email: lihua@email.com
Requires-Python: >3.9.1
Classifier: Intended Audience :: Information Technology
Classifier: Operating System :: Android
Classifier: Operating System :: MacOS
Classifier: Operating System :: Microsoft :: Windows
Classifier: Operating System :: POSIX :: Linux
Classifier: Programming Language :: Python :: 3
Classifier: Programming Language :: Python :: 3.10
Classifier: Programming Language :: Python :: 3.11
Classifier: Programming Language :: Python :: 3.12
Classifier: Programming Language :: Python :: 3.13
Classifier: Topic :: Utilities
Requires-Dist: cryptography (>=45.0.2,<46.0.0)
Requires-Dist: defusedxml (>=0.7.1,<0.8.0)
Requires-Dist: requests (>=2.32.3,<3.0.0)
Project-URL: Bug Tracker, https://github.com/real-LiHua/KeyboxChecker/issues
Project-URL: Repository, https://github.com/real-LiHua/KeyboxChecker
